CLASSIFIERS.txt
LICENSE
MANIFEST.in
README.rst
requirements.pip
setup.py
caldwell_dirtyfields.egg-info/PKG-INFO
caldwell_dirtyfields.egg-info/SOURCES.txt
caldwell_dirtyfields.egg-info/dependency_links.txt
caldwell_dirtyfields.egg-info/top_level.txt
dirtyfields/__init__.py
dirtyfields/dirtyfields.py
dirtyfields/models.py
example_app/__init__.py
example_app/manage.py
example_app/settings.py
example_app/urls.py
example_app/testing_app/__init__.py
example_app/testing_app/models.py
example_app/testing_app/tests.py