Metadata-Version: 1.0
Name: caldwell-dirtyfields
Version: 0.5b1
Summary: Tracking dirty fields on a Django model instance
Home-page: http://github.com/smn/django-dirtyfields
Author: Simon de Haan
Author-email: UNKNOWN
License: BSD
Platform: UNKNOWN
Classifier: Development Status :: 5 - Production/Stable
Classifier: Intended Audience :: Developers
Classifier: License :: OSI Approved :: BSD License
Classifier: Operating System :: OS Independent
Classifier: Programming Language :: Python
Classifier: Framework :: Django
Classifier: Topic :: Software Development :: Libraries :: Python Modules
